{
    "keep": {
        "days": true,
        "amount": 14
    },
    "auditLog": "C:\\Users\\admin\\my-nocobase-app\\storage\\logs\\main\\workflows\\350511677636608\\.d9bdea55e34e51d1b6803e87ada7621bb8234b0e-audit.json",
    "files": [
        {
            "date": 1772161006359,
            "name": "C:\\Users\\admin\\my-nocobase-app\\storage\\logs\\main\\workflows\\350511677636608\\2026-02-27.log",
            "hash": "71dfd8d1f6d4b71a563a32bd4a5f7d23e899e457c35de98e2de4b01f1fe12980"
        },
        {
            "date": 1772499960491,
            "name": "C:\\Users\\admin\\my-nocobase-app\\storage\\logs\\main\\workflows\\350511677636608\\2026-03-03.log",
            "hash": "93ca17ac48baf8f58d81f6148c3d7cf590b877f1972f4fe7a702bd3b300e9ab6"
        }
    ],
    "hashType": "sha256"
}